django_early_return/__init__.py
django_early_return/py.typed
django_early_return/tests/__init__.py
django_early_return/tests/tests.py
django_early_return/tests/urls.py
django_early_return-0.4.0.dist-info/LICENSE
django_early_return-0.4.0.dist-info/METADATA
django_early_return-0.4.0.dist-info/WHEEL
django_early_return-0.4.0.dist-info/top_level.txt
django_early_return-0.4.0.dist-info/RECORD
