Metadata-Version: 2.1
Name: django-early-return
Version: 0.4.0
Summary: Allows view code to exit early and return a given HttpResponse by raising an exception
Home-page: UNKNOWN
Author: Alex Fischer
Author-email: alex@quadrant.net
License: UNKNOWN
Platform: UNKNOWN
Classifier: Programming Language :: Python :: 3
Classifier: License :: OSI Approved :: MIT License
Classifier: Operating System :: OS Independent
Requires-Python: >=3.7
Requires-Dist: Django (<6,>=2.2)
